breez_sdk_spark/__init__.py
breez_sdk_spark/breez_sdk_spark.py
breez_sdk_spark/breez_sdk_spark_bindings.dll
breez_sdk_spark/breez_sdk_spark_bindings.py
breez_sdk_spark/msvcp140.dll
breez_sdk_spark/vcruntime140.dll
breez_sdk_spark-0.7.3.dist-info/METADATA
breez_sdk_spark-0.7.3.dist-info/WHEEL
breez_sdk_spark-0.7.3.dist-info/top_level.txt
breez_sdk_spark-0.7.3.dist-info/RECORD
