Metadata-Version: 2.4
Name: breez_sdk_spark
Version: 0.7.3
Summary: Python language bindings for the Breez Spark SDK
Home-page: https://github.com/breez/spark-sdk
Author: Breez <contact@breez.technology>
License: MIT
Dynamic: author
Dynamic: description
Dynamic: description-content-type
Dynamic: home-page
Dynamic: license
Dynamic: summary
